<?xml version="1.0" encoding="UTF-8"?>
<scene id="id679271" GSCVersion="0.11.0.14" PGFVersion="0.20"><layers><layer id="id112326"><actors><actor id="id395857" prototype="id296877"><attributes><point id="position"><real id="x">160.4609375</real><real id="y">961.98046875</real></point><size id="size"><real id="width">320</real><real id="height">1920</real></size><color id="color"><real id="red">1</real><real id="green">1</real><real id="blue">1</real><real id="alpha">0.5</real></color></attributes><aspects/></actor><actor id="id128207" prototype="id656424"><attributes><point id="position"><real id="x">160</real><real id="y">17</real></point><size id="size"><real id="width">75</real><real id="height">10</real></size><color id="color"><real id="red">1</real><real id="green">1</real><real id="blue">1</real><real id="alpha">1</real></color></attributes><aspects/></actor><actor id="id694437" prototype="id996330"><attributes><point id="position"><real id="x">153.56640625</real><real id="y">1876.859375</real></point><size id="size"><real id="width">64</real><real id="height">64</real></size></attributes><aspects/></actor><actor id="id570258" prototype="id352469"><attributes><point id="position"><real id="x">-7.81640625</real><real id="y">1897.82421875</real></point><size id="size"><real id="width">10</real><real id="height">10</real></size><angle id="rotation">0</angle></attributes><aspects/></actor><actor id="id168677" prototype="id399957"><attributes><point id="position"><real id="x">-7.611328125</real><real id="y">1913.23046875</real></point><size id="size"><real id="width">10</real><real id="height">10</real></size></attributes><aspects><physics><attributes><boolean id="movable">false</boolean></attributes></physics></aspects></actor><actor id="id266541" prototype="id539295"><attributes><text id="name">StarParticles Color Red</text><point id="position"><real id="x">-7.76953125</real><real id="y">1882.99609375</real></point><size id="size"><real id="width">10</real><real id="height">10</real></size><angle id="rotation">0</angle></attributes><aspects/></actor><actor id="id199999" prototype="id539295"><attributes><text id="name">Asteroids</text><point id="position"><real id="x">-39.6796875</real><real id="y">1791.25390625</real></point><size id="size"><real id="width">10</real><real id="height">10</real></size><angle id="rotation">0</angle><color id="color"><real id="red">0</real><real id="green">0</real><real id="blue">1</real><real id="alpha">1</real></color></attributes><aspects/><behaviors><behavior id="id624674" class="TimerBehavior" enabled="true"><attributes><text id="name">Timer</text><text id="bundleName">Timer.behavior</text><index id="timerType">0</index><real id="interval">1</real><boolean id="runToCompletion">false</boolean></attributes><behaviors><behavior id="id554723" class="SpawnAction" enabled="true"><attributes><text id="name">Spawn Actor</text><text id="bundleName">Spawn.behavior</text><text id="prototypeKey">id831709</text><angle id="direction">0</angle><index id="directionSpace">1</index><real id="x"><expression><string xml:space="preserve">0</string></expression></real><real id="y"><expression><string xml:space="preserve">random(640,1900)</string></expression></real><index id="positionSpace">1</index><index id="layerOrder">2</index></attributes></behavior></behaviors></behavior></behaviors></actor><actor id="id450074" prototype="id518465"><attributes><point id="position"><real id="x">161.13671875</real><real id="y">621.83984375</real></point><size id="size"><real id="width">311.1796875</real><real id="height">24</real></size></attributes><aspects/><behaviors><behavior id="id970754" class="TimerBehavior" enabled="true"><attributes><text id="name">Timer</text><text id="bundleName">Timer.behavior</text><index id="timerType">0</index><real id="interval">0</real><boolean id="runToCompletion">false</boolean></attributes><behaviors><behavior id="id720185" class="SpawnAction" enabled="true"><attributes><text id="name">Spawn Actor</text><text id="bundleName">Spawn.behavior</text><text id="prototypeKey">id359776</text><angle id="direction">0</angle><index id="directionSpace">0</index><real id="x"><expression><string xml:space="preserve">random(0,320)</string></expression></real><real id="y">0</real><index id="positionSpace">0</index><index id="layerOrder">2</index></attributes></behavior><behavior id="id497247" class="SpawnAction" enabled="true"><attributes><text id="name">Spawn Actor</text><text id="bundleName">Spawn.behavior</text><text id="prototypeKey">id539918</text><angle id="direction">0</angle><index id="directionSpace">0</index><real id="x"><expression><string xml:space="preserve">random(0,320)</string></expression></real><real id="y">0</real><index id="positionSpace">0</index><index id="layerOrder">2</index></attributes></behavior></behaviors></behavior></behaviors></actor><actor id="id176500" prototype="id716845"><attributes><point id="position"><real id="x">160.712890625</real><real id="y">1934.91796875</real></point><size id="size"><real id="width">320.13671875</real><real id="height">24</real></size></attributes><aspects/></actor></actors><attributes><text id="name">Background</text><boolean id="scrollable">true</boolean></attributes></layer><layer id="id245797"><actors><actor id="id724220" prototype="id286788"><attributes><text id="name">LanderSpeed</text><point id="position"><real id="x">55</real><real id="y">500</real></point><size id="size"><real id="width">100</real><real id="height">30</real></size><angle id="rotation">0</angle></attributes><aspects/><behaviors><behavior id="id370338" class="DisplayTextBehavior" enabled="true"><attributes><text id="name">Display Text</text><text id="bundleName">DisplayText.behavior</text><text id="text">Speed</text><text id="font">American Typewriter</text><real id="size">24</real><index id="alignment">1</index><boolean id="wrap">false</boolean><color id="color"><real id="red">1</real><real id="green">1</real><real id="blue">1</real><real id="alpha">1</real></color><real id="offsetx">0</real><real id="offsety">0</real><index id="space">0</index><index id="directionSpace">0</index><angle id="direction">0</angle></attributes></behavior></behaviors></actor><actor id="id638936" prototype="id466209"><attributes><point id="position"><real id="x">265</real><real id="y">500</real></point><size id="size"><real id="width">100</real><real id="height">30</real></size><angle id="rotation">0</angle></attributes><aspects/><behaviors><behavior id="id370338" class="DisplayTextBehavior" enabled="true"><attributes><text id="name">Display Text</text><text id="bundleName">DisplayText.behavior</text><text id="text">Altitude</text><text id="font">American Typewriter</text><real id="size">22</real><index id="alignment">1</index><boolean id="wrap">false</boolean><color id="color"><real id="red">1</real><real id="green">1</real><real id="blue">1</real><real id="alpha">1</real></color><real id="offsetx">0</real><real id="offsety">0</real><index id="space">0</index><index id="directionSpace">0</index><angle id="direction">0</angle></attributes></behavior><behavior enabled="true" id="id334675" class="RuleBehavior"><attributes><text id="name">Rule</text><text id="bundleName">Rule.behavior</text><real id="compoundConditionKind">0</real></attributes><conditions><condition id="id209843" pluginPredicateTypeIndex="0" eventType="mouse position"><attributes><index id="conditionType">1</index><text id="subjectAttribute">game.attributes.id569220</text></attributes><predicate type="number"><attributes><text id="operator">&lt;=</text><real id="RHS">500</real></attributes></predicate></condition></conditions><behaviors><behavior id="id707286" class="PlaySoundAction" enabled="true"><attributes><text id="name">Play Sound</text><text id="bundleName">PlaySound.behavior</text><sound id="soundName">Warning</sound><boolean id="loop">false</boolean><boolean id="runToCompletion">true</boolean><boolean id="positional">false</boolean><boolean id="dopplerShift">false</boolean><real id="volume">1</real><real id="pitch">1</real></attributes></behavior></behaviors><elseBehaviors/></behavior></behaviors></actor><actor id="id396407" prototype="id902496"><attributes><point id="position"><real id="x">159.6796875</real><real id="y">428.671875</real></point><size id="size"><real id="width">56</real><real id="height">56</real></size><angle id="rotation">0</angle></attributes><aspects/></actor><actor id="id863955" prototype="id448302"><attributes><point id="position"><real id="x">-25.2421875</real><real id="y">260</real></point><size id="size"><real id="width">15</real><real id="height">320</real></size></attributes><aspects/></actor><actor id="id400937" prototype="id559845"><attributes><point id="position"><real id="x">-25.23828125</real><real id="y">260</real></point><size id="size"><real id="width">15</real><real id="height">320</real></size></attributes><aspects/></actor><actor id="id598927" prototype="id162853"><attributes><point id="position"><real id="x">350.21484375</real><real id="y">50</real></point><size id="size"><real id="width">64</real><real id="height">64</real></size><color id="color"><real id="red">1</real><real id="green">1</real><real id="blue">1</real><real id="alpha">1</real></color></attributes><aspects/></actor><actor id="id206780" prototype="id352487"><attributes><point id="position"><real id="x">160</real><real id="y">475</real></point><size id="size"><real id="width">24</real><real id="height">35</real></size><angle id="rotation">0</angle><integer name="Div" id="id726654">100</integer></attributes><aspects/><behaviors><behavior id="id207729" class="ConstrainAttributeBehavior" enabled="true"><attributes><text id="name">Constrain Attribute</text><text id="bundleName">ConstrainAttribute.behavior</text><text id="targetAttribute">self.attributes.image</text><text id="RHS"><expression><string xml:space="preserve">floor((</string><reference keypath="game.attributes.id307433"/><string xml:space="preserve">%</string><reference keypath="self.attributes.id726654"/><string xml:space="preserve">)/(</string><reference keypath="self.attributes.id726654"/><string xml:space="preserve">/10))..&quot;.png&quot;</string></expression></text></attributes></behavior></behaviors></actor><actor id="id769551" prototype="id352487"><attributes><text id="name">Speed</text><point id="position"><real id="x">25</real><real id="y">475</real></point><size id="size"><real id="width">24</real><real id="height">35</real></size><angle id="rotation">0</angle><integer name="Div" id="id726654">10000</integer></attributes><aspects/><behaviors><behavior id="id207729" class="ConstrainAttributeBehavior" enabled="true"><attributes><text name="Name" id="name">Constrain Attribute</text><text name="Bundle Name" id="bundleName">ConstrainAttribute.behavior</text><text name="Target Attribute" id="targetAttribute">self.attributes.image</text><text name="RHS" id="RHS"><expression><string xml:space="preserve">floor((</string><reference keypath="game.attributes.id778643"/><string xml:space="preserve">%</string><reference keypath="self.attributes.id726654"/><string xml:space="preserve">)/(</string><reference keypath="self.attributes.id726654"/><string xml:space="preserve">/10))..&quot;.png&quot;</string></expression></text></attributes></behavior></behaviors></actor><actor id="id307438" prototype="id352487"><attributes><text id="name">Speed</text><point id="position"><real id="x">45</real><real id="y">475</real></point><size id="size"><real id="width">24</real><real id="height">35</real></size><angle id="rotation">0</angle><integer name="Div" id="id726654">1000</integer></attributes><aspects/><behaviors><behavior id="id207729" class="ConstrainAttributeBehavior" enabled="true"><attributes><text name="Name" id="name">Constrain Attribute</text><text name="Bundle Name" id="bundleName">ConstrainAttribute.behavior</text><text name="Target Attribute" id="targetAttribute">self.attributes.image</text><text name="RHS" id="RHS"><expression><string xml:space="preserve">floor((</string><reference keypath="game.attributes.id778643"/><string xml:space="preserve">%</string><reference keypath="self.attributes.id726654"/><string xml:space="preserve">)/(</string><reference keypath="self.attributes.id726654"/><string xml:space="preserve">/10))..&quot;.png&quot;</string></expression></text></attributes></behavior></behaviors></actor><actor id="id350540" prototype="id352487"><attributes><text id="name">Speed</text><point id="position"><real id="x">65</real><real id="y">475</real></point><size id="size"><real id="width">24</real><real id="height">35</real></size><angle id="rotation">0</angle><integer name="Div" id="id726654">100</integer></attributes><aspects/><behaviors><behavior id="id207729" class="ConstrainAttributeBehavior" enabled="true"><attributes><text name="Name" id="name">Constrain Attribute</text><text name="Bundle Name" id="bundleName">ConstrainAttribute.behavior</text><text name="Target Attribute" id="targetAttribute">self.attributes.image</text><text name="RHS" id="RHS"><expression><string xml:space="preserve">floor((</string><reference keypath="game.attributes.id778643"/><string xml:space="preserve">%</string><reference keypath="self.attributes.id726654"/><string xml:space="preserve">)/(</string><reference keypath="self.attributes.id726654"/><string xml:space="preserve">/10))..&quot;.png&quot;</string></expression></text></attributes></behavior></behaviors></actor><actor id="id779070" prototype="id352487"><attributes><text id="name">Speed</text><point id="position"><real id="x">85</real><real id="y">475</real></point><size id="size"><real id="width">24</real><real id="height">35</real></size><angle id="rotation">0</angle></attributes><aspects/><behaviors><behavior id="id207729" class="ConstrainAttributeBehavior" enabled="true"><attributes><text name="Name" id="name">Constrain Attribute</text><text name="Bundle Name" id="bundleName">ConstrainAttribute.behavior</text><text name="Target Attribute" id="targetAttribute">self.attributes.image</text><text name="RHS" id="RHS"><expression><string xml:space="preserve">floor((</string><reference keypath="game.attributes.id778643"/><string xml:space="preserve">%</string><reference keypath="self.attributes.id726654"/><string xml:space="preserve">)/(</string><reference keypath="self.attributes.id726654"/><string xml:space="preserve">/10))..&quot;.png&quot;</string></expression></text></attributes></behavior></behaviors></actor><actor id="id461404" prototype="id352487"><attributes><text id="name">Alt</text><point id="position"><real id="x">295</real><real id="y">475</real></point><size id="size"><real id="width">24</real><real id="height">35</real></size></attributes><aspects/><behaviors><behavior id="id207729" class="ConstrainAttributeBehavior" enabled="true"><attributes><text name="Name" id="name">Constrain Attribute</text><text name="Bundle Name" id="bundleName">ConstrainAttribute.behavior</text><text name="Target Attribute" id="targetAttribute">self.attributes.image</text><text name="RHS" id="RHS"><expression><string xml:space="preserve">floor((</string><reference keypath="game.attributes.id569220"/><string xml:space="preserve">%</string><reference keypath="self.attributes.id726654"/><string xml:space="preserve">)/(</string><reference keypath="self.attributes.id726654"/><string xml:space="preserve">/10))..&quot;.png&quot;</string></expression></text></attributes></behavior></behaviors></actor><actor id="id118270" prototype="id352487"><attributes><text id="name">Alt</text><point id="position"><real id="x">275</real><real id="y">475</real></point><size id="size"><real id="width">24</real><real id="height">35</real></size><integer name="Div" id="id726654">100</integer></attributes><aspects/><behaviors><behavior id="id207729" class="ConstrainAttributeBehavior" enabled="true"><attributes><text name="Name" id="name">Constrain Attribute</text><text name="Bundle Name" id="bundleName">ConstrainAttribute.behavior</text><text name="Target Attribute" id="targetAttribute">self.attributes.image</text><text name="RHS" id="RHS"><expression><string xml:space="preserve">floor((</string><reference keypath="game.attributes.id569220"/><string xml:space="preserve">%</string><reference keypath="self.attributes.id726654"/><string xml:space="preserve">)/(</string><reference keypath="self.attributes.id726654"/><string xml:space="preserve">/10))..&quot;.png&quot;</string></expression></text></attributes></behavior></behaviors></actor><actor id="id703245" prototype="id352487"><attributes><text id="name">Alt</text><point id="position"><real id="x">255</real><real id="y">475</real></point><size id="size"><real id="width">24</real><real id="height">35</real></size><image id="image"></image><integer name="Div" id="id726654">1000</integer></attributes><aspects/><behaviors><behavior id="id207729" class="ConstrainAttributeBehavior" enabled="true"><attributes><text name="Name" id="name">Constrain Attribute</text><text name="Bundle Name" id="bundleName">ConstrainAttribute.behavior</text><text name="Target Attribute" id="targetAttribute">self.attributes.image</text><text name="RHS" id="RHS"><expression><string xml:space="preserve">floor((</string><reference keypath="game.attributes.id569220"/><string xml:space="preserve">%</string><reference keypath="self.attributes.id726654"/><string xml:space="preserve">)/(</string><reference keypath="self.attributes.id726654"/><string xml:space="preserve">/10))..&quot;.png&quot;</string></expression></text></attributes></behavior></behaviors></actor><actor id="id973752" prototype="id352487"><attributes><text id="name">Alt</text><point id="position"><real id="x">235</real><real id="y">475</real></point><size id="size"><real id="width">24</real><real id="height">35</real></size><image id="image"></image><integer name="Div" id="id726654">10000</integer></attributes><aspects/><behaviors><behavior id="id207729" class="ConstrainAttributeBehavior" enabled="true"><attributes><text name="Name" id="name">Constrain Attribute</text><text name="Bundle Name" id="bundleName">ConstrainAttribute.behavior</text><text name="Target Attribute" id="targetAttribute">self.attributes.image</text><text name="RHS" id="RHS"><expression><string xml:space="preserve">floor((</string><reference keypath="game.attributes.id569220"/><string xml:space="preserve">%</string><reference keypath="self.attributes.id726654"/><string xml:space="preserve">)/(</string><reference keypath="self.attributes.id726654"/><string xml:space="preserve">/10))..&quot;.png&quot;</string></expression></text></attributes></behavior></behaviors></actor><actor id="id965351" prototype="id352487"><attributes><point id="position"><real id="x">141</real><real id="y">475</real></point><size id="size"><real id="width">24</real><real id="height">35</real></size><angle id="rotation">0</angle><integer name="Div" id="id726654">1000</integer></attributes><aspects/><behaviors><behavior id="id207729" class="ConstrainAttributeBehavior" enabled="true"><attributes><text id="name">Constrain Attribute</text><text id="bundleName">ConstrainAttribute.behavior</text><text id="targetAttribute">self.attributes.image</text><text id="RHS"><expression><string xml:space="preserve">floor((</string><reference keypath="game.attributes.id307433"/><string xml:space="preserve">%</string><reference keypath="self.attributes.id726654"/><string xml:space="preserve">)/(</string><reference keypath="self.attributes.id726654"/><string xml:space="preserve">/10))..&quot;.png&quot;</string></expression></text></attributes></behavior></behaviors></actor><actor id="id933861" prototype="id352487"><attributes><point id="position"><real id="x">179</real><real id="y">475</real></point><size id="size"><real id="width">24</real><real id="height">35</real></size><angle id="rotation">0</angle></attributes><aspects/><behaviors><behavior id="id207729" class="ConstrainAttributeBehavior" enabled="true"><attributes><text id="name">Constrain Attribute</text><text id="bundleName">ConstrainAttribute.behavior</text><text id="targetAttribute">self.attributes.image</text><text id="RHS"><expression><string xml:space="preserve">floor((</string><reference keypath="game.attributes.id307433"/><string xml:space="preserve">%</string><reference keypath="self.attributes.id726654"/><string xml:space="preserve">)/(</string><reference keypath="self.attributes.id726654"/><string xml:space="preserve">/10))..&quot;.png&quot;</string></expression></text></attributes></behavior></behaviors></actor></actors><attributes><text id="name">UI</text><boolean id="scrollable">false</boolean></attributes></layer></layers><attributes><text id="name">Main Game copy</text><real id="time">0</real><size id="size"><real id="width">320</real><real id="height">1920</real></size><boolean id="wrapX">false</boolean><boolean id="wrapY">false</boolean><point id="gravity"><real id="x">0</real><real id="y">300</real></point><color id="color"><real id="red">0</real><real id="green">0</real><real id="blue">0</real><real id="alpha">1</real></color><rect id="camera"><point id="origin"><real id="x">0</real><real id="y">0</real></point><size id="size"><real id="width">320</real><real id="height">520</real></size><size id="trackingArea"><real id="width">238</real><real id="height">9.5625</real></size><real id="rotation">0</real></rect><attributes id="autorotate"><boolean id="landscapeLeft">false</boolean><boolean id="portrait">true</boolean><boolean id="landscapeRight">false</boolean><boolean id="portraitUpsideDown">false</boolean></attributes></attributes></scene>
